[
  {
    "id": 1,
    "name": "Geometric Harmony Tote",
    "price": 2499,
    "colors": ["terracotta", "beige"],
    "printStyle": "blockprint",
    "image": "https://images.unsplash.com/photo-1553062407-98eeb64c6a62?ixlib=rb-4.0.3&auto=format&fit=crop&w=400&h=400",
    "description": "A beautifully crafted tote bag featuring traditional geometric block prints on premium organic cotton. Perfect for daily use with spacious interior and comfortable handles.",
    "care": "100% organic cotton. Machine wash cold with like colors. Tumble dry low. Iron on medium heat.",
    "rating": 5,
    "reviewCount": 24,
    "dimensions": "40cm W × 35cm H × 10cm D. Handle drop: 25cm. Perfect for daily essentials and more.",
    "inStock": true
  },
  {
    "id": 2,
    "name": "Royal Paisley Tote",
    "price": 2799,
    "colors": ["mustard", "maroon"],
    "printStyle": "paisley",
    "image": "https://images.unsplash.com/photo-1591561954557-26941169b49e?ixlib=rb-4.0.3&auto=format&fit=crop&w=400&h=400",
    "description": "Elegant paisley patterns that celebrate the royal heritage of Indian textile art. Crafted with attention to detail and premium materials.",
    "care": "100% organic cotton. Hand wash recommended for best results. Air dry in shade. Iron on low heat.",
    "rating": 4,
    "reviewCount": 18,
    "dimensions": "42cm W × 36cm H × 12cm D. Handle drop: 26cm. Spacious design for all your needs.",
    "inStock": true
  },
  {
    "id": 3,
    "name": "Mandala Meditation Tote",
    "price": 3199,
    "colors": ["maroon", "sage"],
    "printStyle": "mandala",
    "image": "https://images.unsplash.com/photo-1566150905458-1bf1fc113f0d?ixlib=rb-4.0.3&auto=format&fit=crop&w=400&h=400",
    "description": "Intricate mandala designs that bring spiritual energy to your everyday style. Each pattern is carefully hand-blocked by master artisans.",
    "care": "100% organic cotton. Gentle machine wash cold. Lay flat to dry. Steam iron for best results.",
    "rating": 5,
    "reviewCount": 31,
    "dimensions": "38cm W × 34cm H × 8cm D. Handle drop: 24cm. Compact yet functional design.",
    "inStock": true
  },
  {
    "id": 4,
    "name": "Zen Garden Tote",
    "price": 2299,
    "colors": ["sage", "beige"],
    "printStyle": "blockprint",
    "image": "https://images.unsplash.com/photo-1584464491033-06628f3a6b7b?ixlib=rb-4.0.3&auto=format&fit=crop&w=400&h=400",
    "description": "Minimalist block prints inspired by zen philosophy and natural beauty. Perfect for those who appreciate subtle elegance.",
    "care": "100% organic cotton. Machine wash cold with mild detergent. Tumble dry low. Iron as needed.",
    "rating": 4,
    "reviewCount": 15,
    "dimensions": "39cm W × 33cm H × 9cm D. Handle drop: 23cm. Minimalist design with maximum utility.",
    "inStock": true
  },
  {
    "id": 5,
    "name": "Spice Route Tote",
    "price": 2899,
    "colors": ["terracotta", "mustard"],
    "printStyle": "paisley",
    "image": "https://images.unsplash.com/photo-1493723843671-1d655e66ac1c?ixlib=rb-4.0.3&auto=format&fit=crop&w=400&h=400",
    "description": "Warm spice-inspired colors with paisley patterns that tell tales of ancient trade routes. A fusion of history and style.",
    "care": "100% organic cotton. Cold wash recommended. Air dry for longevity. Iron on medium heat.",
    "rating": 5,
    "reviewCount": 27,
    "dimensions": "41cm W × 35cm H × 11cm D. Handle drop: 25cm. Perfect balance of style and function.",
    "inStock": true
  },
  {
    "id": 6,
    "name": "Heritage Mandala Tote",
    "price": 3599,
    "colors": ["maroon", "beige"],
    "printStyle": "mandala",
    "image": "https://images.unsplash.com/photo-1524863479829-916d8e77f114?ixlib=rb-4.0.3&auto=format&fit=crop&w=400&h=400",
    "description": "Our premium mandala collection piece, showcasing the finest traditional craftsmanship. A true work of art that doubles as a functional accessory.",
    "care": "100% premium organic cotton. Professional dry cleaning recommended. Store in dust bag when not in use.",
    "rating": 5,
    "reviewCount": 42,
    "dimensions": "43cm W × 37cm H × 13cm D. Handle drop: 27cm. Premium design for discerning customers.",
    "inStock": true
  },
  {
    "id": 7,
    "name": "Artisan's Pride Tote",
    "price": 2699,
    "colors": ["sage", "mustard"],
    "printStyle": "blockprint",
    "image": "https://images.unsplash.com/photo-1556905055-8f358a7a47b2?ixlib=rb-4.0.3&auto=format&fit=crop&w=400&h=400",
    "description": "Celebrating the pride of our artisans with bold block print designs that showcase generations of skill and tradition.",
    "care": "100% organic cotton. Machine wash cold separately. Air dry recommended. Iron on reverse side.",
    "rating": 4,
    "reviewCount": 19,
    "dimensions": "40cm W × 34cm H × 10cm D. Handle drop: 24cm. Artisan-inspired design.",
    "inStock": true
  },
  {
    "id": 8,
    "name": "Desert Bloom Tote",
    "price": 2999,
    "colors": ["beige", "terracotta"],
    "printStyle": "paisley",
    "image": "https://images.unsplash.com/photo-1594736797933-d0300536d178?ixlib=rb-4.0.3&auto=format&fit=crop&w=400&h=400",
    "description": "Inspired by the desert's resilient beauty, featuring delicate paisley motifs that bloom across the canvas like flowers in the sand.",
    "care": "100% organic cotton. Gentle cycle wash cold. Flat dry in shade. Steam iron for best finish.",
    "rating": 5,
    "reviewCount": 33,
    "dimensions": "41cm W × 36cm H × 12cm D. Handle drop: 26cm. Desert-inspired elegance.",
    "inStock": true
  }
]
